Metadata-Version: 1.0
Name: templer.zope
Version: 1.0b2
Summary: Templer system extensions for zope
Home-page: http://svn.plone.org/svn/collective/
Author: Cris Ewing
Author-email: cris@crisewing.com
License: MIT
Keywords: zope buildout
Platform: UNKNOWN
Classifier: Development Status :: 4 - Beta
Classifier: Framework :: Zope2
Classifier: Framework :: Buildout
Classifier: Intended Audience :: Developers
Classifier: License :: OSI Approved :: MIT License
Classifier: Programming Language :: Python
Classifier: Programming Language :: Python :: 2.4
Classifier: Programming Language :: Python :: 2.5
Classifier: Programming Language :: Python :: 2.6
Classifier: Topic :: Internet :: WWW/HTTP
Classifier: Topic :: Internet :: WWW/HTTP :: Dynamic Content
Classifier: Topic :: Software Development :: Code Generators
